srelogging.py
srelogging-0.0.3.dist-info/METADATA
srelogging-0.0.3.dist-info/WHEEL
srelogging-0.0.3.dist-info/top_level.txt
srelogging-0.0.3.dist-info/RECORD
