Metadata-Version: 2.1
Name: srelogging
Version: 0.0.3
Summary: Common logging functions for SRE python scripts.
Home-page: UNKNOWN
Author: Figglewatts
Author-email: sgibson@glasswallsolutions.com
License: UNKNOWN
Keywords: sre logging
Platform: UNKNOWN
Classifier: Programming Language :: Python :: 3.7
Classifier: License :: OSI Approved :: MIT License
Classifier: Development Status :: 4 - Beta
Classifier: Intended Audience :: Developers
Classifier: Operating System :: OS Independent
Classifier: Topic :: System :: Logging
Requires-Python: >=3.6
Requires-Dist: pyyaml
